dio_osny_processamento_imagem/__init__.py
dio_osny_processamento_imagem/processing/__init__.py
dio_osny_processamento_imagem/processing/combination.py
dio_osny_processamento_imagem/processing/transformation.py
dio_osny_processamento_imagem/utils/__init__.py
dio_osny_processamento_imagem/utils/io.py
dio_osny_processamento_imagem/utils/plot.py
dio_osny_processamento_imagem-0.0.1.dist-info/METADATA
dio_osny_processamento_imagem-0.0.1.dist-info/WHEEL
dio_osny_processamento_imagem-0.0.1.dist-info/top_level.txt
dio_osny_processamento_imagem-0.0.1.dist-info/RECORD
