Metadata-Version: 2.4
Name: dio_osny_processamento_imagem
Version: 0.0.1
Summary: Processamento de imagens com Python
Home-page: https://github.com/OsnyNeto/Programas_Python/tree/main/dio_osny_processamento_imagem
Author: Osny MSN
Author-email: osnynt@gmail.com
Requires-Python: >=3.8
Dynamic: author
Dynamic: author-email
Dynamic: description
Dynamic: description-content-type
Dynamic: home-page
Dynamic: requires-python
Dynamic: summary
